[
    {
        "model": "roamapi.status",
        "pk": 1,
        "fields": {
            "type": "Home"
        }
    },
    {
        "model": "roamapi.status",
        "pk": 2,
        "fields": {
            "type": "FinalDestination"
        }
    },
    {
        "model": "roamapi.status",
        "pk": 3,
        "fields": {
            "type": "Stop"
        }
    },
    {
        "model": "roamapi.status",
        "pk": 4,
        "fields": {
            "type": "Favorite"
        }
    }, 
    {
        "model": "roamapi.status",
        "pk": 5,
        "fields": {
            "type": "To-Go"
        }
    }
]